readme_weaver/__init__.py
readme_weaver/include_content_reader.py
readme_weaver/include_metadata.py
readme_weaver/include_metadata_extractor.py
readme_weaver/main.py
readme_weaver/readme_weaver.py
readme_weaver-0.1.1.dist-info/METADATA
readme_weaver-0.1.1.dist-info/WHEEL
readme_weaver-0.1.1.dist-info/entry_points.txt
readme_weaver-0.1.1.dist-info/licenses/LICENSE
readme_weaver-0.1.1.dist-info/RECORD
