Metadata-Version: 2.4
Name: readme-weaver
Version: 0.1.1
Summary: Embed raw markdown partials into README files
Project-URL: Home, https://github.com/devops-roast/readme-weaver
Author-email: Oleksandr Ponomarov  <ponomarov.aleksandr@gmail.com>
License:                                  Apache License
License-File: LICENSE
Requires-Python: >=3.13
Requires-Dist: loguru>=0.7.3
Requires-Dist: typer-slim>=0.16.1
Provides-Extra: all
Requires-Dist: pytest>=8.4.1; extra == 'all'
Requires-Dist: ruff>=0.12.11; extra == 'all'
